mp_string_sim/__init__.py
mp_string_sim/string_similarity.py
mp_string_similarity-3.0.1.dist-info/METADATA
mp_string_similarity-3.0.1.dist-info/WHEEL
mp_string_similarity-3.0.1.dist-info/pbr.json
mp_string_similarity-3.0.1.dist-info/top_level.txt
mp_string_similarity-3.0.1.dist-info/RECORD
